amaasinfra/__init__.py
amaasinfra/config.py
amaasinfra/authorization/__init__.py
amaasinfra/authorization/amaas_user.py
amaasinfra/authorization/token_utils.py
amaasinfra/communication/__init__.py
amaasinfra/communication/cache_publisher.py
amaasinfra/communication/publisher.py
amaasinfra/communication/queue_publisher.py
amaasinfra/communication/subscriber.py
amaasinfra/config/__init__.py
amaasinfra/config/amaas_config.py
amaasinfra/data/__init__.py
amaasinfra/data/data_setup.py
amaasinfra/data/dynamodb.py
amaasinfra/email/__init__.py
amaasinfra/email/templates.py
amaasinfra/email/transactional.py
amaasinfra/exception/__init__.py
amaasinfra/exception/message.py
amaasinfra/infra/__init__.py
amaasinfra/infra/credential/__init__.py
amaasinfra/infra/credential/cognito.py
amaasinfra/infra/credential/policy.py
amaasinfra/infra/credential/sts.py
amaasinfra/infra/elasticsearch/__init__.py
amaasinfra/infra/elasticsearch/elasticsearch_proxy.py
amaasinfra/infra/lambda/__init__.py
amaasinfra/infra/lambda/config.py
amaasinfra/infra/lambda/sfn_lambda_proxy.py
amaasinfra/infra/management/__init__.py
amaasinfra/infra/management/manager.py
amaasinfra/infra/messaging/__init__.py
amaasinfra/infra/messaging/config.py
amaasinfra/infra/messaging/iot.py
amaasinfra/infra/messaging/sns.py
amaasinfra/infra/messaging/sqs.py
amaasinfra/infra/notification/__init__.py
amaasinfra/infra/s3/__init__.py
amaasinfra/infra/s3/s3_object.py
amaasinfra/logging/__init__.py
amaasinfra/logging/api_call.py
amaasinfra-0.4.3.dist-info/DESCRIPTION.rst
amaasinfra-0.4.3.dist-info/METADATA
amaasinfra-0.4.3.dist-info/RECORD
amaasinfra-0.4.3.dist-info/WHEEL
amaasinfra-0.4.3.dist-info/metadata.json
amaasinfra-0.4.3.dist-info/top_level.txt
tests/__init__.py
tests/amaas_user.py
