Metadata-Version: 2.0
Name: amaasinfra
Version: 0.4.3
Summary: This is an essential package for managing AMaaS infra layer.
Home-page: UNKNOWN
Author: AMaaS Pte Ltd
Author-email: tech@argomi.com
License: Apache License 2.0
Keywords: amaas,infra,aws
Platform: any
Requires-Dist: aws-requests-auth
Requires-Dist: boto3
Requires-Dist: configparser
Requires-Dist: elasticsearch-dsl
Requires-Dist: pyjwt
Requires-Dist: pymysql
Requires-Dist: requests
